django_routeview/__init__.py
django_routeview-1.1.0.dist-info/LICENSE
django_routeview-1.1.0.dist-info/METADATA
django_routeview-1.1.0.dist-info/WHEEL
django_routeview-1.1.0.dist-info/top_level.txt
django_routeview-1.1.0.dist-info/RECORD
