Metadata-Version: 2.1
Name: django-routeview
Version: 1.1.0
Summary: A RouteView class which register itself
Home-page: https://github.com/TiphaineLAURENT/Django_RouteView
Author: Tiphaine LAURENT
Author-email: tip.lau@hotmail.fr
License: BSD
Platform: any
Classifier: Environment :: Web Environment
Classifier: Intended Audience :: Developers
Classifier: License :: OSI Approved :: BSD License
Classifier: Operating System :: OS Independent
Classifier: Programming Language :: Python
Classifier: Topic :: Internet :: WWW/HTTP :: Dynamic Content
Classifier: Topic :: Software Development :: Libraries :: Python Modules
Requires-Python: >=3.6
Requires-Dist: Django
